{
  "appveyor": "7.9.2",
  "base": "7.9.2",
  "conda": "7.9.2",
  "coverage": "7.9.2",
  "coveralls": "7.9.2",
  "data": "7.9.2",
  "doc": "7.9.2",
  "flake8": "7.9.2",
  "git": "7.9.2",
  "github": "7.9.2",
  "landscape": "7.9.2",
  "lgtm": "7.9.2",
  "license": "7.9.2",
  "notebook": "7.9.2",
  "pypi": "7.9.2",
  "pyproject": "7.9.2",
  "readthedocs": "7.9.2",
  "reqs": "7.9.2",
  "requires": "7.9.2",
  "sphinx": "7.9.2",
  "src": "7.9.2",
  "test": "7.9.2",
  "tox": "7.9.2",
  "travis": "7.9.2",
  "version": "7.9.2"
}