{
  "_pkglts": {
    "auto_install": true,
    "install_front_end": "stdout",
    "use_prompts": false,
    "version": 12
  },
  "appveyor": {
    "token": "hrwjhn2oe0q4oaf2"
  },
  "base": {
    "authors": [
      [
        "revesansparole",
        "revesansparole@gmail.com"
      ]
    ],
    "namespace": null,
    "namespace_method": "pkg_util",
    "pkgname": "pkglts",
    "url": null
  },
  "conda": {},
  "coverage": {},
  "coveralls": {},
  "data": {
    "filetype": [
      "",
      ".bat",
      ".cfg",
      ".json",
      ".md",
      ".in",
      ".ini",
      ".png",
      ".ps1",
      ".rst",
      ".sh",
      ".tpl",
      ".txt",
      ".yaml",
      ".yml"
    ],
    "use_ext_dir": false
  },
  "doc": {
    "description": "Building packages with long term support",
    "fmt": "rst",
    "keywords": [
      "packaging",
      "package builder"
    ]
  },
  "flake8": {},
  "git": {},
  "github": {
    "owner": "{{ base.authors[0][0] }}",
    "project": "{{ base.pkgname }}",
    "url": "https://github.com/{{ github.owner }}/{{ github.project }}"
  },
  "landscape": {},
  "license": {
    "name": "CeCILL-C",
    "organization": "OpenAlea",
    "project": "{{ base.pkgname }}",
    "year": "2015"
  },
  "notebook": {
    "src_directory": "example"
  },
  "pypi": {
    "classifiers": [
      "Development Status :: 2 - Pre-Alpha",
      "Intended Audience :: Developers",
      "License :: OSI Approved :: BSD License",
      "Natural Language :: English"
    ],
    "servers": [
      {
        "name": "pypi",
        "url": "https://upload.pypi.org/legacy/"
      },
      {
        "name": "test",
        "url": "https://testpypi.python.org/pypi"
      }
    ]
  },
  "pysetup": {
    "intended_versions": [
      "27",
      "35",
      "36"
    ],
    "require": [
      {
        "name": "jinja2"
      },
      {
        "name": "requests"
      },
      {
        "channel": "conda-forge",
        "name": "semver"
      },
      {
        "name": "unidecode"
      }
    ]
  },
  "readthedocs": {
    "project": "{{ github.project }}"
  },
  "requires": {},
  "sphinx": {
    "autodoc_dvlpt": true,
    "build_dir": "build/sphinx",
    "theme": "sphinx_rtd_theme"
  },
  "test": {
    "suite_name": "pytest"
  },
  "tox": {},
  "travis": {},
  "version": {
    "major": 3,
    "minor": 5,
    "post": 2
  }
}